<?xml version="1.0" encoding="UTF-8"?>
<!DOCTYPE mapper PUBLIC "-//mybatis.org//DTD Mapper 3.0//EN" "http://mybatis.org/dtd/mybatis-3-mapper.dtd">
<mapper namespace="com.tgy.rtls.data.mapper.promoter.PromoterLogMapper">
  <resultMap id="BaseResultMap" type="com.tgy.rtls.data.entity.promoter.PromoterLog">
    <!--@mbg.generated-->
    <!--@Table promoter_log-->
    <id column="id" jdbcType="INTEGER" property="id" />
    <result column="pro_info_id" jdbcType="INTEGER" property="proInfoId" />
    <result column="dest_id" jdbcType="INTEGER" property="destId" />
    <result column="shangjia_name" jdbcType="VARCHAR" property="shangjiaName" />
    <result column="map" jdbcType="VARCHAR" property="map" />
    <result column="map_name" jdbcType="VARCHAR" property="mapName" />
    <result column="desc" jdbcType="VARCHAR" property="desc" />
  </resultMap>
  <sql id="Base_Column_List">
    <!--@mbg.generated-->
    id, pro_info_id, dest_id, shangjia_name, `map`, map_name, `desc`
  </sql>
</mapper>